movoid_config/__init__.py
movoid_config/config.py
movoid_config/loop_run.py
movoid_config-1.2.6.dist-info/METADATA
movoid_config-1.2.6.dist-info/WHEEL
movoid_config-1.2.6.dist-info/top_level.txt
movoid_config-1.2.6.dist-info/RECORD
