Metadata-Version: 2.1
Name: movoid_config
Version: 1.2.6
Home-page: 
Author: movoid
Author-email: bobrobotsun@163.com
